.gitignore
.travis.yml
CHANGES.txt
LICENSE.txt
README.rst
setup.cfg
setup.py
tox.ini
ptahcms/__init__.py
ptahcms/blob.py
ptahcms/container.py
ptahcms/content.py
ptahcms/form-actions.pt
ptahcms/forms.py
ptahcms/interfaces.py
ptahcms/node.py
ptahcms/permissions.py
ptahcms/rest.py
ptahcms/restsrv.py
ptahcms/root.py
ptahcms/security.py
ptahcms/tinfo.py
ptahcms/traverser.py
ptahcms.egg-info/PKG-INFO
ptahcms.egg-info/SOURCES.txt
ptahcms.egg-info/dependency_links.txt
ptahcms.egg-info/not-zip-safe
ptahcms.egg-info/requires.txt
ptahcms.egg-info/top_level.txt
ptahcms/manage/__init__.py
ptahcms/manage/apps.py
ptahcms/manage/model.py
ptahcms/manage/rest.py
ptahcms/manage/templates/apps-contentview.pt
ptahcms/manage/templates/apps-layout.pt
ptahcms/manage/templates/apps-sharing.pt
ptahcms/manage/templates/apps.pt
ptahcms/manage/templates/model-add.pt
ptahcms/manage/templates/model-edit.pt
ptahcms/manage/templates/model.pt
ptahcms/manage/templates/models.pt
ptahcms/manage/templates/rest.pt
ptahcms/manage/tests/test_apps.py
ptahcms/manage/tests/test_model.py
ptahcms/manage/tests/test_restinsp.py
ptahcms/tests/test_application.py
ptahcms/tests/test_blobstorage.py
ptahcms/tests/test_container.py
ptahcms/tests/test_content.py
ptahcms/tests/test_forms.py
ptahcms/tests/test_loadapi.py
ptahcms/tests/test_node.py
ptahcms/tests/test_rest.py
ptahcms/tests/test_restsrv.py
ptahcms/tests/test_schema.py
ptahcms/tests/test_security.py
ptahcms/tests/test_tinfo.py
ptahcms/tests/test_traverser.py